zhinst/timing_models/__init__.py
zhinst/timing_models/_version.py
zhinst/timing_models/common.py
zhinst/timing_models/feedback_model.py
zhinst/timing_models/output_models.py
zhinst/timing_models/py.typed
zhinst/timing_models/trigger_latencies.yml
zhinst_timing_models-26.1.0.dist-info/METADATA
zhinst_timing_models-26.1.0.dist-info/WHEEL
zhinst_timing_models-26.1.0.dist-info/licenses/LICENSE.txt
zhinst_timing_models-26.1.0.dist-info/RECORD
