Metadata-Version: 2.4
Name: zhinst-timing-models
Version: 26.1.0
Summary: Feedback Data Latency model for PQSC, SHF- and HDAWG systems.
Author-email: Zurich Instruments <info@zhinst.com>
License-Expression: MIT
License-File: LICENSE.txt
Keywords: zhinst
Classifier: Development Status :: 4 - Beta
Classifier: Programming Language :: Python
Classifier: Programming Language :: Python :: 3.8
Classifier: Programming Language :: Python :: 3.9
Classifier: Programming Language :: Python :: 3.10
Classifier: Programming Language :: Python :: 3.11
Requires-Python: >=3.8
Requires-Dist: numpy>=1.14
Requires-Dist: pyyaml>=6.0.1
